{
	"$schema": "https://developer.microsoft.com/json-schemas/rush/v5/rush.schema.json",
	"rushVersion": "5.131.0",
	"yarnVersion": "1.22.19",
	"nodeSupportedVersionRange": ">=18.20.3 <19.0.0 || >=20.10.0 <21.0.0",
	"projects": [
		{
			"packageName": "platform",
			"projectFolder": "packages/platform"
		},
		{
			"packageName": "node",
			"projectFolder": "server/node"
		},
		{
			"packageName": "golang-core",
			"projectFolder": "server/golang"
		}
	],
	"npmOptions": {
		"environmentVariables": {
			"registry": {
				"value": "https://registry.npmmirror.com"
			}
		}
	},
	"yarnOptions": {
		"environmentVariables": {
			"registry": {
				"value": "https://registry.npmmirror.com"
			}
		}
	}
}
